ScratchToPython/__init__.py
ScratchToPython/myfunctions.py
scratch_py/__init__.py
scratch_py/colour.py
scratch_py/manager.py
scratch_py/rotation.py
scratch_py/sprite.py
scratch_to_python-0.1.2.dist-info/METADATA
scratch_to_python-0.1.2.dist-info/WHEEL
scratch_to_python-0.1.2.dist-info/top_level.txt
scratch_to_python-0.1.2.dist-info/RECORD
